mindscope_utilities/__init__.py
mindscope_utilities/general_utilities.py
mindscope_utilities/plotting_utilities.py
mindscope_utilities/behavior/__init__.py
mindscope_utilities/visual_behavior_ophys/__init__.py
mindscope_utilities/visual_behavior_ophys/data_formatting.py
mindscope_utilities/visual_behavior_ophys/plotting_utilities.py
mindscope_utilities-0.1.9.dist-info/LICENSE
mindscope_utilities-0.1.9.dist-info/METADATA
mindscope_utilities-0.1.9.dist-info/WHEEL
mindscope_utilities-0.1.9.dist-info/top_level.txt
mindscope_utilities-0.1.9.dist-info/RECORD
